{"kind":"Notebook","sha256":"61353501064ae0cd15cea7fdd8a34dc1c18de708f80248618768bd35f40735ac","slug":"quickstart","location":"/home/runner/work/connattractor/connattractor/docs/02-quickstart.ipynb","dependencies":[],"frontmatter":{"title":"Quickstart","license":{"content":{"id":"CC-BY-4.0","name":"Creative Commons Attribution 4.0 International","free":true,"CC":true,"url":"https://creativecommons.org/licenses/by/4.0/"}},"github":"https://github.com/pni-lab/connattractor","keywords":[],"exports":[{"format":"ipynb","filename":"02-quickstart.ipynb","url":"/02-quickstart-aad0974a31d2a5aa5b20df148eeeafa6.ipynb"}]},"mdast":{"type":"root","children":[{"type":"block","children":[{"type":"paragraph","position":{"start":{"line":2,"column":0},"end":{"line":3,"column":0}},"children":[{"type":"emphasis","children":[{"type":"strong","children":[{"type":"text","value":"for Connectivity-based Hopfield Neural Networks (CHNNs)","key":"JbB2VCBYUj"}],"key":"vgivkhcS5Q"}],"key":"al5GvwiPVI"}],"key":"NJsAjKU8t5"},{"type":"list","ordered":false,"spread":false,"position":{"start":{"line":4,"column":0},"end":{"line":6,"column":0}},"children":[{"type":"listItem","spread":true,"position":{"start":{"line":4,"column":0},"end":{"line":5,"column":0}},"children":[{"type":"strong","children":[{"type":"text","value":"Part 1","key":"T3HoqURSJO"}],"key":"PEm5CN2aGI"},{"type":"text","value":": The quickest way to plot and analyze your data on the CHNN projection","key":"E9PiWrdu2c"}],"key":"UarWKGotRf"},{"type":"listItem","spread":true,"position":{"start":{"line":5,"column":0},"end":{"line":6,"column":0}},"children":[{"type":"strong","children":[{"type":"text","value":"Part 2","key":"py01I42SZu"}],"key":"Cl62IopUjc"},{"type":"text","value":": Build your own CHNN projection","key":"X2dUcGwr0C"}],"key":"bQDFIHYgcJ"}],"key":"RgIicx176n"}],"data":{"type":"notebook-content"},"key":"j9tqfIXxiH"},{"type":"block","children":[{"type":"paragraph","position":{"start":{"line":0,"column":0},"end":{"line":1,"column":0}},"children":[{"type":"strong","children":[{"type":"text","value":"Imports","key":"jtuOhj4IHe"}],"key":"vhFpLs4jzi"}],"key":"zh2guPHD2K"}],"data":{"type":"notebook-content"},"key":"od0XvRuxwu"},{"type":"block","children":[{"type":"code","lang":"python","executable":true,"value":"import sys\nsys.path.append('..')\nimport pandas as pd\nimport seaborn as sns\nfrom connattractor import network, analysis","key":"peQ0fhywqm"},{"type":"output","id":"7AhUONCkleRPnYNyqIHOO","data":[],"key":"txAXzvTdvp"}],"data":{"type":"notebook-code","ExecuteTime":{"end_time":"2023-08-21T16:31:16.104879Z","start_time":"2023-08-21T16:31:15.942684Z"}},"key":"MQ1UtyPkCk"},{"type":"block","children":[{"type":"heading","depth":2,"position":{"start":{"line":0,"column":0},"end":{"line":1,"column":0}},"children":[{"type":"text","value":"Part 1: The quickest way to plot and analyze your data on the CHNN projection","key":"J5tH6uX1lz"}],"identifier":"part-1-the-quickest-way-to-plot-and-analyze-your-data-on-the-chnn-projection","label":"Part 1: The quickest way to plot and analyze your data on the CHNN projection","html_id":"part-1-the-quickest-way-to-plot-and-analyze-your-data-on-the-chnn-projection","implicit":true,"key":"ec1hlhrfRk"}],"data":{"type":"notebook-content"},"key":"ThoIrbXRAI"},{"type":"block","children":[{"type":"heading","depth":4,"position":{"start":{"line":0,"column":0},"end":{"line":1,"column":0}},"children":[{"type":"text","value":"todo:","key":"jF1uC8C2FG"}],"identifier":"todo","label":"todo:","html_id":"todo","implicit":true,"key":"REj5xQfrYZ"},{"type":"list","ordered":false,"spread":false,"position":{"start":{"line":2,"column":0},"end":{"line":6,"column":0}},"children":[{"type":"listItem","spread":true,"position":{"start":{"line":2,"column":0},"end":{"line":3,"column":0}},"children":[{"type":"text","value":"load a pre-computed embedding","key":"yf2N3ahitq"}],"key":"qs8Os8Sa7d"},{"type":"listItem","spread":true,"position":{"start":{"line":3,"column":0},"end":{"line":4,"column":0}},"children":[{"type":"text","value":"load some example data","key":"WUm0YqrSXZ"}],"key":"KGNdSLKMAD"},{"type":"listItem","spread":true,"position":{"start":{"line":4,"column":0},"end":{"line":5,"column":0}},"children":[{"type":"text","value":"plot it in the embedding","key":"HwJ66wyFMw"}],"key":"QjwGJCDbQI"},{"type":"listItem","spread":true,"position":{"start":{"line":5,"column":0},"end":{"line":6,"column":0}},"children":[{"type":"text","value":"do a simple permutation test","key":"TBLiYlcet8"}],"key":"ssWVDRcUpd"}],"key":"a3QPYtzWa6"}],"data":{"type":"notebook-content"},"key":"C8mzec0ae9"},{"type":"block","children":[{"type":"heading","depth":2,"position":{"start":{"line":0,"column":0},"end":{"line":1,"column":0}},"children":[{"type":"text","value":"Part 2: Build your own CHNN projection","key":"d6UiZHp7dM"}],"identifier":"part-2-build-your-own-chnn-projection","label":"Part 2: Build your own CHNN projection","html_id":"part-2-build-your-own-chnn-projection","implicit":true,"key":"FXqiiRbrbL"}],"data":{"type":"notebook-content"},"key":"AeiBJ86MPz"},{"type":"block","children":[{"type":"heading","depth":3,"position":{"start":{"line":0,"column":0},"end":{"line":1,"column":0}},"children":[{"type":"text","value":"Obtain functional connectivity matrix","key":"YV3uaLi1ue"}],"identifier":"obtain-functional-connectivity-matrix","label":"Obtain functional connectivity matrix","html_id":"obtain-functional-connectivity-matrix","implicit":true,"key":"NVaryE3eue"},{"type":"paragraph","position":{"start":{"line":2,"column":0},"end":{"line":3,"column":0}},"children":[{"type":"text","value":"Should be a partial correlation matrix, square and symmetric.","key":"jvsFBbjSrs"}],"key":"Cx3KuAPdf9"},{"type":"paragraph","position":{"start":{"line":4,"column":0},"end":{"line":6,"column":0}},"children":[{"type":"text","value":"Below, we load in an example connectome, derived from study 1 of the manuscript.\nGiven the high replicability and generalizability of CHNN analyses, the connectome does not have to stem from the analyzed dataset. Similarly to anatomical standrad templates in neuroimaging practice, the supplied example connectome can be considered a standard connectome template.","key":"mTValUdP9G"}],"key":"m6rMGAEXqo"},{"type":"paragraph","position":{"start":{"line":7,"column":0},"end":{"line":8,"column":0}},"children":[{"type":"text","value":"Users are, nevertheless, encouraged to use dataset-specific connectomes.","key":"h3CzLVblAs"}],"key":"vF64yQssJD"},{"type":"heading","depth":4,"position":{"start":{"line":9,"column":0},"end":{"line":10,"column":0}},"children":[{"type":"text","value":"Let's load in the example connectome","key":"LOBQkYEvy9"}],"identifier":"let-s-load-in-the-example-connectome","label":"Let's load in the example connectome","html_id":"let-s-load-in-the-example-connectome","implicit":true,"key":"SFmYeL78ti"}],"data":{"type":"notebook-content"},"key":"qG106dDg7J"},{"type":"block","children":[{"type":"code","lang":"python","executable":true,"value":"connfile = '../data_in/ex_connectome_partial_correlation.csv'\nmtx = pd.read_csv(connfile).iloc[:, 1:]\nmtx","key":"PKS3puGOk1"},{"type":"output","id":"EWQmZo3advbZpnWEZb2SG","data":[{"output_type":"execute_result","execution_count":6,"metadata":{},"data":{"text/html":{"content":"<div>\n<style scoped>\n    .dataframe tbody tr th:only-of-type {\n        vertical-align: middle;\n    }\n\n    .dataframe tbody tr th {\n        vertical-align: top;\n    }\n\n    .dataframe thead th {\n        text-align: right;\n    }\n</style>\n<table border=\"1\" class=\"dataframe\">\n  <thead>\n    <tr style=\"text-align: right;\">\n      <th></th>\n      <th>CER6_p</th>\n      <th>CER7ab</th>\n      <th>R_CERCR2_p</th>\n      <th>CER9_v</th>\n      <th>CER6_a</th>\n      <th>L_CERCR2_a</th>\n      <th>CER9_d</th>\n      <th>CER9_m</th>\n      <th>CER7b_m</th>\n      <th>L_CERCR2_p</th>\n      <th>...</th>\n      <th>LVISnet_vp</th>\n      <th>MVISnet_p</th>\n      <th>MVISnet_av</th>\n      <th>LVISnet_p</th>\n      <th>PVISnet_dm</th>\n      <th>PVISnet_vm</th>\n      <th>MVISnet_ad</th>\n      <th>VVISnet_l</th>\n      <th>LVISnet_DP</th>\n      <th>VVISnet_m</th>\n    </tr>\n  </thead>\n  <tbody>\n    <tr>\n      <th>0</th>\n      <td>1.000000</td>\n      <td>0.023502</td>\n      <td>0.136701</td>\n      <td>0.008193</td>\n      <td>0.074264</td>\n      <td>0.021580</td>\n      <td>0.170827</td>\n      <td>0.028969</td>\n      <td>0.015883</td>\n      <td>0.130981</td>\n      <td>...</td>\n      <td>-0.002248</td>\n      <td>-0.008683</td>\n      <td>0.000152</td>\n      <td>0.035482</td>\n      <td>0.007705</td>\n      <td>-0.029055</td>\n      <td>0.009439</td>\n      <td>-0.001390</td>\n      <td>0.009582</td>\n      <td>0.007318</td>\n    </tr>\n    <tr>\n      <th>1</th>\n      <td>0.023502</td>\n      <td>1.000000</td>\n      <td>0.008167</td>\n      <td>0.024126</td>\n      <td>0.046648</td>\n      <td>0.050263</td>\n      <td>0.010915</td>\n      <td>0.070042</td>\n      <td>0.085829</td>\n      <td>-0.018248</td>\n      <td>...</td>\n      <td>0.033791</td>\n      <td>0.004000</td>\n      <td>0.011493</td>\n      <td>0.007582</td>\n      <td>-0.026080</td>\n      <td>0.008013</td>\n      <td>-0.009007</td>\n      <td>0.009144</td>\n      <td>0.001391</td>\n      <td>0.012831</td>\n    </tr>\n    <tr>\n      <th>2</th>\n      <td>0.136701</td>\n      <td>0.008167</td>\n      <td>1.000000</td>\n      <td>0.005056</td>\n      <td>0.062669</td>\n      <td>0.028488</td>\n      <td>0.041643</td>\n      <td>0.045169</td>\n      <td>0.112164</td>\n      <td>0.157129</td>\n      <td>...</td>\n      <td>-0.003300</td>\n      <td>0.016258</td>\n      <td>-0.011801</td>\n      <td>-0.001794</td>\n      <td>-0.000603</td>\n      <td>0.012350</td>\n      <td>-0.002757</td>\n      <td>-0.004949</td>\n      <td>-0.004858</td>\n      <td>-0.000633</td>\n    </tr>\n    <tr>\n      <th>3</th>\n      <td>0.008193</td>\n      <td>0.024126</td>\n      <td>0.005056</td>\n      <td>1.000000</td>\n      <td>-0.020494</td>\n      <td>-0.008721</td>\n      <td>-0.004522</td>\n      <td>0.203525</td>\n      <td>-0.003757</td>\n      <td>0.019182</td>\n      <td>...</td>\n      <td>0.021645</td>\n      <td>0.000472</td>\n      <td>-0.003774</td>\n      <td>0.003395</td>\n      <td>-0.032710</td>\n      <td>-0.015305</td>\n      <td>0.007360</td>\n      <td>0.004044</td>\n      <td>-0.011696</td>\n      <td>-0.001293</td>\n    </tr>\n    <tr>\n      <th>4</th>\n      <td>0.074264</td>\n      <td>0.046648</td>\n      <td>0.062669</td>\n      <td>-0.020494</td>\n      <td>1.000000</td>\n      <td>0.080293</td>\n      <td>0.024584</td>\n      <td>0.002491</td>\n      <td>-0.021720</td>\n      <td>0.042291</td>\n      <td>...</td>\n      <td>-0.020753</td>\n      <td>0.005295</td>\n      <td>-0.012844</td>\n      <td>-0.014833</td>\n      <td>0.009989</td>\n      <td>0.024167</td>\n      <td>-0.005186</td>\n      <td>-0.016061</td>\n      <td>0.010920</td>\n      <td>-0.007650</td>\n    </tr>\n    <tr>\n      <th>...</th>\n      <td>...</td>\n      <td>...</td>\n      <td>...</td>\n      <td>...</td>\n      <td>...</td>\n      <td>...</td>\n      <td>...</td>\n      <td>...</td>\n      <td>...</td>\n      <td>...</td>\n      <td>...</td>\n      <td>...</td>\n      <td>...</td>\n      <td>...</td>\n      <td>...</td>\n      <td>...</td>\n      <td>...</td>\n      <td>...</td>\n      <td>...</td>\n      <td>...</td>\n      <td>...</td>\n    </tr>\n    <tr>\n      <th>117</th>\n      <td>-0.029055</td>\n      <td>0.008013</td>\n      <td>0.012350</td>\n      <td>-0.015305</td>\n      <td>0.024167</td>\n      <td>-0.007512</td>\n      <td>0.045950</td>\n      <td>0.010056</td>\n      <td>-0.006412</td>\n      <td>-0.000421</td>\n      <td>...</td>\n      <td>0.011186</td>\n      <td>0.215436</td>\n      <td>-0.011083</td>\n      <td>-0.003814</td>\n      <td>0.163692</td>\n      <td>1.000000</td>\n      <td>0.013773</td>\n      <td>0.049101</td>\n      <td>-0.028493</td>\n      <td>0.115196</td>\n    </tr>\n    <tr>\n      <th>118</th>\n      <td>0.009439</td>\n      <td>-0.009007</td>\n      <td>-0.002757</td>\n      <td>0.007360</td>\n      <td>-0.005186</td>\n      <td>-0.023476</td>\n      <td>-0.004195</td>\n      <td>-0.029927</td>\n      <td>-0.023948</td>\n      <td>-0.023841</td>\n      <td>...</td>\n      <td>-0.012657</td>\n      <td>0.258308</td>\n      <td>0.091981</td>\n      <td>0.007686</td>\n      <td>-0.001867</td>\n      <td>0.013773</td>\n      <td>1.000000</td>\n      <td>-0.013407</td>\n      <td>0.017465</td>\n      <td>0.032366</td>\n    </tr>\n    <tr>\n      <th>119</th>\n      <td>-0.001390</td>\n      <td>0.009144</td>\n      <td>-0.004949</td>\n      <td>0.004044</td>\n      <td>-0.016061</td>\n      <td>0.004057</td>\n      <td>0.002311</td>\n      <td>-0.022643</td>\n      <td>0.001888</td>\n      <td>-0.007811</td>\n      <td>...</td>\n      <td>0.139682</td>\n      <td>-0.014010</td>\n      <td>0.077810</td>\n      <td>0.079338</td>\n      <td>0.055300</td>\n      <td>0.049101</td>\n      <td>-0.013407</td>\n      <td>1.000000</td>\n      <td>0.081084</td>\n      <td>0.162297</td>\n    </tr>\n    <tr>\n      <th>120</th>\n      <td>0.009582</td>\n      <td>0.001391</td>\n      <td>-0.004858</td>\n      <td>-0.011696</td>\n      <td>0.010920</td>\n      <td>0.002928</td>\n      <td>-0.001322</td>\n      <td>0.004114</td>\n      <td>-0.006720</td>\n      <td>-0.008002</td>\n      <td>...</td>\n      <td>0.066451</td>\n      <td>0.001324</td>\n      <td>-0.001214</td>\n      <td>0.115287</td>\n      <td>0.089609</td>\n      <td>-0.028493</td>\n      <td>0.017465</td>\n      <td>0.081084</td>\n      <td>1.000000</td>\n      <td>0.000165</td>\n    </tr>\n    <tr>\n      <th>121</th>\n      <td>0.007318</td>\n      <td>0.012831</td>\n      <td>-0.000633</td>\n      <td>-0.001293</td>\n      <td>-0.007650</td>\n      <td>0.026176</td>\n      <td>-0.012108</td>\n      <td>-0.008898</td>\n      <td>-0.002792</td>\n      <td>-0.002899</td>\n      <td>...</td>\n      <td>0.024625</td>\n      <td>0.088237</td>\n      <td>0.171533</td>\n      <td>0.016583</td>\n      <td>0.043844</td>\n      <td>0.115196</td>\n      <td>0.032366</td>\n      <td>0.162297</td>\n      <td>0.000165</td>\n      <td>1.000000</td>\n    </tr>\n  </tbody>\n</table>\n<p>122 rows × 122 columns</p>\n</div>","content_type":"text/html"},"text/plain":{"content":"       CER6_p    CER7ab  R_CERCR2_p    CER9_v    CER6_a  L_CERCR2_a    CER9_d  \\\n0    1.000000  0.023502    0.136701  0.008193  0.074264    0.021580  0.170827   \n1    0.023502  1.000000    0.008167  0.024126  0.046648    0.050263  0.010915   \n2    0.136701  0.008167    1.000000  0.005056  0.062669    0.028488  0.041643   \n3    0.008193  0.024126    0.005056  1.000000 -0.020494   -0.008721 -0.004522   \n4    0.074264  0.046648    0.062669 -0.020494  1.000000    0.080293  0.024584   \n..        ...       ...         ...       ...       ...         ...       ...   \n117 -0.029055  0.008013    0.012350 -0.015305  0.024167   -0.007512  0.045950   \n118  0.009439 -0.009007   -0.002757  0.007360 -0.005186   -0.023476 -0.004195   \n119 -0.001390  0.009144   -0.004949  0.004044 -0.016061    0.004057  0.002311   \n120  0.009582  0.001391   -0.004858 -0.011696  0.010920    0.002928 -0.001322   \n121  0.007318  0.012831   -0.000633 -0.001293 -0.007650    0.026176 -0.012108   \n\n       CER9_m   CER7b_m  L_CERCR2_p  ...  LVISnet_vp  MVISnet_p  MVISnet_av  \\\n0    0.028969  0.015883    0.130981  ...   -0.002248  -0.008683    0.000152   \n1    0.070042  0.085829   -0.018248  ...    0.033791   0.004000    0.011493   \n2    0.045169  0.112164    0.157129  ...   -0.003300   0.016258   -0.011801   \n3    0.203525 -0.003757    0.019182  ...    0.021645   0.000472   -0.003774   \n4    0.002491 -0.021720    0.042291  ...   -0.020753   0.005295   -0.012844   \n..        ...       ...         ...  ...         ...        ...         ...   \n117  0.010056 -0.006412   -0.000421  ...    0.011186   0.215436   -0.011083   \n118 -0.029927 -0.023948   -0.023841  ...   -0.012657   0.258308    0.091981   \n119 -0.022643  0.001888   -0.007811  ...    0.139682  -0.014010    0.077810   \n120  0.004114 -0.006720   -0.008002  ...    0.066451   0.001324   -0.001214   \n121 -0.008898 -0.002792   -0.002899  ...    0.024625   0.088237    0.171533   \n\n     LVISnet_p  PVISnet_dm  PVISnet_vm  MVISnet_ad  VVISnet_l  LVISnet_DP  \\\n0     0.035482    0.007705   -0.029055    0.009439  -0.001390    0.009582   \n1     0.007582   -0.026080    0.008013   -0.009007   0.009144    0.001391   \n2    -0.001794   -0.000603    0.012350   -0.002757  -0.004949   -0.004858   \n3     0.003395   -0.032710   -0.015305    0.007360   0.004044   -0.011696   \n4    -0.014833    0.009989    0.024167   -0.005186  -0.016061    0.010920   \n..         ...         ...         ...         ...        ...         ...   \n117  -0.003814    0.163692    1.000000    0.013773   0.049101   -0.028493   \n118   0.007686   -0.001867    0.013773    1.000000  -0.013407    0.017465   \n119   0.079338    0.055300    0.049101   -0.013407   1.000000    0.081084   \n120   0.115287    0.089609   -0.028493    0.017465   0.081084    1.000000   \n121   0.016583    0.043844    0.115196    0.032366   0.162297    0.000165   \n\n     VVISnet_m  \n0     0.007318  \n1     0.012831  \n2    -0.000633  \n3    -0.001293  \n4    -0.007650  \n..         ...  \n117   0.115196  \n118   0.032366  \n119   0.162297  \n120   0.000165  \n121   1.000000  \n\n[122 rows x 122 columns]","content_type":"text/plain"}}}],"key":"PF2m2bnhnH"}],"data":{"type":"notebook-code","ExecuteTime":{"end_time":"2023-08-21T16:32:22.601047Z","start_time":"2023-08-21T16:32:22.546256Z"}},"key":"c4tAO6mxzy"},{"type":"block","children":[{"type":"heading","depth":4,"position":{"start":{"line":0,"column":0},"end":{"line":1,"column":0}},"children":[{"type":"text","value":"Now we construct a CHNN and plot the weights","key":"bnoBSANxWf"}],"identifier":"now-we-construct-a-chnn-and-plot-the-weights","label":"Now we construct a CHNN and plot the weights","html_id":"now-we-construct-a-chnn-and-plot-the-weights","implicit":true,"key":"ngn6AKS52Z"}],"data":{"type":"notebook-content"},"key":"LqJRiSx8Kk"},{"type":"block","children":[{"type":"code","lang":"python","executable":true,"value":"hopnet = network.Hopfield(mtx)\nhopnet.plot_weights()","key":"UDMAIoG7t5"},{"type":"output","id":"gC354yyc_hYUkTL0I-V3s","data":[{"output_type":"display_data","metadata":{"needs_background":"light"},"data":{"image/png":{"content_type":"image/png","hash":"0205aa1fc1cf9ca0b21354f3949f387e","path":"/0205aa1fc1cf9ca0b21354f3949f387e.png"},"text/plain":{"content":"<Figure size 432x360 with 2 Axes>","content_type":"text/plain"}}}],"key":"bZAt0l5dky"}],"data":{"type":"notebook-code","ExecuteTime":{"end_time":"2023-08-21T16:34:51.827031Z","start_time":"2023-08-21T16:34:51.489089Z"}},"key":"GgXibgfsym"},{"type":"block","children":[{"type":"heading","depth":4,"position":{"start":{"line":0,"column":0},"end":{"line":1,"column":0}},"children":[{"type":"text","value":"Now we run the stochastic relaxation procedure to obtain simulated states","key":"TTLXNkClKt"}],"identifier":"now-we-run-the-stochastic-relaxation-procedure-to-obtain-simulated-states","label":"Now we run the stochastic relaxation procedure to obtain simulated states","html_id":"now-we-run-the-stochastic-relaxation-procedure-to-obtain-simulated-states","implicit":true,"key":"s7oYNrE5Sw"},{"type":"paragraph","position":{"start":{"line":1,"column":0},"end":{"line":2,"column":0}},"children":[{"type":"text","value":"It may take a few seconds...","key":"x2VWQPHc1r"}],"key":"D8FVnCbYiw"}],"data":{"type":"notebook-content","ExecuteTime":{"end_time":"2023-08-21T16:35:32.422191Z","start_time":"2023-08-21T16:35:32.419696Z"}},"key":"vlDbmj8SBC"},{"type":"block","children":[{"type":"code","lang":"python","executable":true,"value":"chnn_state_space = analysis.simulate_activations(mtx.values,\n                                            noise_coef=0.37,\n                                            num_iter=100000,\n                                            beta=0.04,\n                                            random_state=42)","key":"R9yvuiqSWw"},{"type":"output","id":"qbhuz5bSSMfey8FiCJzFR","data":[{"name":"stderr","output_type":"stream","text":"100%|██████████| 100000/100000 [00:17<00:00, 5733.25it/s]\n"}],"key":"kQMQHiQyJA"}],"data":{"type":"notebook-code","ExecuteTime":{"end_time":"2023-08-21T16:44:39.716101Z","start_time":"2023-08-21T16:44:22.264954Z"}},"key":"q5ovTo0lbU"},{"type":"block","children":[{"type":"heading","depth":4,"position":{"start":{"line":0,"column":0},"end":{"line":1,"column":0}},"children":[{"type":"text","value":"We create a Hopfield Embedding","key":"wHf2Tm2F6c"}],"identifier":"we-create-a-hopfield-embedding","label":"We create a Hopfield Embedding","html_id":"we-create-a-hopfield-embedding","implicit":true,"key":"N07NzhpQbx"},{"type":"paragraph","position":{"start":{"line":1,"column":0},"end":{"line":2,"column":0}},"children":[{"type":"text","value":"Again, a few seconds...","key":"VyzoIgijs3"}],"key":"jiqp3RRHSn"}],"data":{"type":"notebook-content","ExecuteTime":{"end_time":"2023-08-21T16:37:38.466307Z","start_time":"2023-08-21T16:37:38.460513Z"}},"key":"feaaemSRlz"},{"type":"block","children":[{"type":"code","lang":"python","executable":true,"value":"chnn_projection = analysis.create_embeddings(chnn_state_space,\n                                             attractor_sample=1000,\n                                             random_state=42)","key":"R8vRhlm5wM"},{"type":"output","id":"CkW5HurANKk9SLdDhCsVT","data":[{"name":"stderr","output_type":"stream","text":"100%|██████████| 1000/1000 [00:38<00:00, 25.76it/s]\n"}],"key":"WzM6vkh12O"}],"data":{"type":"notebook-code","ExecuteTime":{"end_time":"2023-08-21T16:45:55.879874Z","start_time":"2023-08-21T16:45:14.184761Z"}},"key":"eWhzofR7Rj"},{"type":"block","children":[{"type":"heading","depth":4,"position":{"start":{"line":0,"column":0},"end":{"line":1,"column":0}},"children":[{"type":"text","value":"and plot the state space in it","key":"rYOT9awGod"}],"identifier":"and-plot-the-state-space-in-it","label":"and plot the state space in it","html_id":"and-plot-the-state-space-in-it","implicit":true,"key":"s4XJy8GP1G"}],"data":{"type":"notebook-content"},"key":"FH4su6L3sH"},{"type":"block","children":[{"type":"code","lang":"python","executable":true,"value":"ax = chnn_projection.plot(chnn_state_space.states, plot_type='contourf',\n                          density_bins=30, density_sigma=0.5, levels=12, alpha=0.8, cmap='Greens',\n                          attractor_plot_type='glassbrain', attractor_kwargs=dict(cmap='binary'),\n                          regimes_fill_kwargs=dict(alpha=0.0),\n                          regimes_contour_kwargs=dict(alpha=1.0, colors='black')\n                         )\nax.set_yticks([])\nax.grid(False)","key":"wJMZVjpWrx"},{"type":"output","id":"yC1cQSQBGGthaHpczjR9s","data":[{"output_type":"display_data","metadata":{"needs_background":"light"},"data":{"image/png":{"content_type":"image/png","hash":"148a46280dcc01cc97f0e9cec49125db","path":"/148a46280dcc01cc97f0e9cec49125db.png"},"text/plain":{"content":"<Figure size 288x288 with 10 Axes>","content_type":"text/plain"}}}],"key":"yR8CZ10RzI"}],"data":{"type":"notebook-code","ExecuteTime":{"end_time":"2023-08-21T16:48:42.956690Z","start_time":"2023-08-21T16:48:31.603657Z"}},"key":"DxZZnQiS8F"}],"key":"wlrAf5pLgj"},"references":{"cite":{"order":[],"data":{}}}}